{
  "last_updated": "2026-03-30T01:59:30Z",
  "market_status": "open",
  "total_market_cap": 2024165.0,
  "stocks": {
    "react": {
      "full_name": "facebook/react",
      "price": 733.44,
      "prev_price": 750.68,
      "change_pct": -2.3,
      "volume_24h": 22,
      "market_cap": 366720.0,
      "shares_outstanding": 500,
      "ipo_date": "2026-03-22",
      "metrics": {
        "stars": 244260,
        "forks": 50870,
        "commits_week": 10,
        "issue_response_hrs": 4600.2,
        "contributors": 411
      },
      "tags": []
    },
    "vscode": {
      "full_name": "microsoft/vscode",
      "price": 632.93,
      "prev_price": 616.26,
      "change_pct": 2.71,
      "volume_24h": 3,
      "market_cap": 316465.0,
      "shares_outstanding": 500,
      "ipo_date": "2026-03-22",
      "metrics": {
        "stars": 183167,
        "forks": 38827,
        "commits_week": 24,
        "issue_response_hrs": 137.9,
        "contributors": 324
      },
      "tags": []
    },
    "deno": {
      "full_name": "denoland/deno",
      "price": 427.74,
      "prev_price": 401.89,
      "change_pct": 6.43,
      "volume_24h": 2,
      "market_cap": 213870.0,
      "shares_outstanding": 500,
      "ipo_date": "2026-03-22",
      "metrics": {
        "stars": 106443,
        "forks": 5983,
        "commits_week": 2,
        "issue_response_hrs": 5943.6,
        "contributors": 432
      },
      "tags": []
    },
    "nextjs": {
      "full_name": "vercel/next.js",
      "price": 386.47,
      "prev_price": 493.47,
      "change_pct": -21.68,
      "volume_24h": 5,
      "market_cap": 193235.0,
      "shares_outstanding": 500,
      "ipo_date": "2026-03-22",
      "metrics": {
        "stars": 138523,
        "forks": 30722,
        "commits_week": 1,
        "issue_response_hrs": 27313.6,
        "contributors": 429
      },
      "tags": []
    },
    "svelte": {
      "full_name": "sveltejs/svelte",
      "price": 388.74,
      "prev_price": 400.93,
      "change_pct": -3.04,
      "volume_24h": 6,
      "market_cap": 194370.0,
      "shares_outstanding": 500,
      "ipo_date": "2026-03-22",
      "metrics": {
        "stars": 86129,
        "forks": 4833,
        "commits_week": 3,
        "issue_response_hrs": 4567.3,
        "contributors": 411
      },
      "tags": []
    },
    "autoresearch": {
      "full_name": "karpathy/autoresearch",
      "price": 249.52,
      "prev_price": 249.64,
      "change_pct": -0.05,
      "volume_24h": 0,
      "market_cap": 124760.0,
      "shares_outstanding": 500,
      "ipo_date": "2026-03-22",
      "metrics": {
        "stars": 60652,
        "forks": 8460,
        "commits_week": 1,
        "issue_response_hrs": 35.9,
        "contributors": 8
      },
      "tags": [
        "ipo-new"
      ]
    },
    "gstack": {
      "full_name": "garrytan/gstack",
      "price": 254.99,
      "prev_price": 237.01,
      "change_pct": 7.59,
      "volume_24h": 20,
      "market_cap": 127495.0,
      "shares_outstanding": 500,
      "ipo_date": "2026-03-22",
      "metrics": {
        "stars": 55756,
        "forks": 7273,
        "commits_week": 3,
        "issue_response_hrs": 168.0,
        "contributors": 5
      },
      "tags": [
        "ipo-new"
      ]
    },
    "paperclip": {
      "full_name": "paperclipai/paperclip",
      "price": 471.78,
      "prev_price": 484.68,
      "change_pct": -2.66,
      "volume_24h": 0,
      "market_cap": 235890.0,
      "shares_outstanding": 500,
      "ipo_date": "2026-03-22",
      "metrics": {
        "stars": 39147,
        "forks": 5791,
        "commits_week": 196,
        "issue_response_hrs": 168.0,
        "contributors": 49
      },
      "tags": [
        "ipo-new"
      ]
    },
    "cli": {
      "full_name": "googleworkspace/cli",
      "price": 239.66,
      "prev_price": 246.95,
      "change_pct": -2.95,
      "volume_24h": 0,
      "market_cap": 119830.0,
      "shares_outstanding": 500,
      "ipo_date": "2026-03-22",
      "metrics": {
        "stars": 23067,
        "forks": 1125,
        "commits_week": 38,
        "issue_response_hrs": 105.7,
        "contributors": 42
      },
      "tags": [
        "ipo-new"
      ]
    },
    "clianything": {
      "full_name": "HKUDS/CLI-Anything",
      "price": 263.06,
      "prev_price": 259.53,
      "change_pct": 1.36,
      "volume_24h": 5,
      "market_cap": 131530.0,
      "shares_outstanding": 500,
      "ipo_date": "2026-03-22",
      "metrics": {
        "stars": 24730,
        "forks": 2216,
        "commits_week": 52,
        "issue_response_hrs": 121.3,
        "contributors": 37
      },
      "tags": [
        "ipo-new"
      ]
    }
  }
}
