{
  "last_updated": "2026-04-26T06:40:24Z",
  "market_status": "open",
  "total_market_cap": 3001745.0,
  "stocks": {
    "react": {
      "full_name": "facebook/react",
      "price": 585.1,
      "prev_price": 705.47,
      "change_pct": -17.06,
      "volume_24h": 22,
      "market_cap": 292550.0,
      "shares_outstanding": 500,
      "ipo_date": "2026-03-22",
      "metrics": {
        "stars": 244683,
        "forks": 50982,
        "commits_week": 5,
        "issue_response_hrs": 5459.0,
        "contributors": 411
      },
      "tags": []
    },
    "vscode": {
      "full_name": "microsoft/vscode",
      "price": 851.31,
      "prev_price": 689.32,
      "change_pct": 23.5,
      "volume_24h": 3,
      "market_cap": 425655.0,
      "shares_outstanding": 500,
      "ipo_date": "2026-03-22",
      "metrics": {
        "stars": 184273,
        "forks": 39439,
        "commits_week": 637,
        "issue_response_hrs": 774.1,
        "contributors": 322
      },
      "tags": []
    },
    "deno": {
      "full_name": "denoland/deno",
      "price": 418.82,
      "prev_price": 414.54,
      "change_pct": 1.03,
      "volume_24h": 2,
      "market_cap": 209410.0,
      "shares_outstanding": 500,
      "ipo_date": "2026-03-22",
      "metrics": {
        "stars": 106538,
        "forks": 6032,
        "commits_week": 9,
        "issue_response_hrs": 1020.1,
        "contributors": 433
      },
      "tags": []
    },
    "nextjs": {
      "full_name": "vercel/next.js",
      "price": 580.62,
      "prev_price": 580.08,
      "change_pct": 0.09,
      "volume_24h": 5,
      "market_cap": 290310.0,
      "shares_outstanding": 500,
      "ipo_date": "2026-03-22",
      "metrics": {
        "stars": 139165,
        "forks": 30970,
        "commits_week": 52,
        "issue_response_hrs": 0.0,
        "contributors": 428
      },
      "tags": []
    },
    "svelte": {
      "full_name": "sveltejs/svelte",
      "price": 347.56,
      "prev_price": 393.51,
      "change_pct": -11.68,
      "volume_24h": 6,
      "market_cap": 173780.0,
      "shares_outstanding": 500,
      "ipo_date": "2026-03-22",
      "metrics": {
        "stars": 86425,
        "forks": 4896,
        "commits_week": 4,
        "issue_response_hrs": 2109.8,
        "contributors": 411
      },
      "tags": []
    },
    "autoresearch": {
      "full_name": "karpathy/autoresearch",
      "price": 284.14,
      "prev_price": 274.12,
      "change_pct": 3.66,
      "volume_24h": 0,
      "market_cap": 142070.0,
      "shares_outstanding": 500,
      "ipo_date": "2026-03-22",
      "metrics": {
        "stars": 76655,
        "forks": 11180,
        "commits_week": 0,
        "issue_response_hrs": 168.0,
        "contributors": 9
      },
      "tags": [
        "ipo-new"
      ]
    },
    "gstack": {
      "full_name": "garrytan/gstack",
      "price": 281.56,
      "prev_price": 299.96,
      "change_pct": -6.13,
      "volume_24h": 20,
      "market_cap": 140780.0,
      "shares_outstanding": 500,
      "ipo_date": "2026-03-22",
      "metrics": {
        "stars": 83473,
        "forks": 12175,
        "commits_week": 18,
        "issue_response_hrs": 202.8,
        "contributors": 9
      },
      "tags": [
        "ipo-new"
      ]
    },
    "paperclip": {
      "full_name": "paperclipai/paperclip",
      "price": 300.59,
      "prev_price": 299.83,
      "change_pct": 0.25,
      "volume_24h": 0,
      "market_cap": 150295.0,
      "shares_outstanding": 500,
      "ipo_date": "2026-03-22",
      "metrics": {
        "stars": 58889,
        "forks": 10234,
        "commits_week": 53,
        "issue_response_hrs": 0.2,
        "contributors": 83
      },
      "tags": [
        "ipo-new"
      ]
    },
    "cli": {
      "full_name": "googleworkspace/cli",
      "price": 193.42,
      "prev_price": 200.79,
      "change_pct": -3.67,
      "volume_24h": 0,
      "market_cap": 96710.0,
      "shares_outstanding": 500,
      "ipo_date": "2026-03-22",
      "metrics": {
        "stars": 25395,
        "forks": 1300,
        "commits_week": 0,
        "issue_response_hrs": 0.1,
        "contributors": 43
      },
      "tags": [
        "ipo-new"
      ]
    },
    "clianything": {
      "full_name": "HKUDS/CLI-Anything",
      "price": 230.11,
      "prev_price": 230.32,
      "change_pct": -0.09,
      "volume_24h": 5,
      "market_cap": 115055.0,
      "shares_outstanding": 500,
      "ipo_date": "2026-03-22",
      "metrics": {
        "stars": 32609,
        "forks": 3173,
        "commits_week": 32,
        "issue_response_hrs": 13.6,
        "contributors": 64
      },
      "tags": [
        "ipo-new"
      ]
    },
    "pretext": {
      "full_name": "chenglou/pretext",
      "price": 215.46,
      "prev_price": 217.26,
      "change_pct": -0.83,
      "volume_24h": 0,
      "market_cap": 107730.0,
      "shares_outstanding": 500,
      "ipo_date": "2026-04-01",
      "metrics": {
        "stars": 45366,
        "forks": 2498,
        "commits_week": 9,
        "issue_response_hrs": 245.7,
        "contributors": 7
      },
      "tags": [
        "ipo-new"
      ]
    },
    "nemoclaw": {
      "full_name": "NVIDIA/NemoClaw",
      "price": 279.3,
      "prev_price": 303.69,
      "change_pct": -8.03,
      "volume_24h": 0,
      "market_cap": 139650.0,
      "shares_outstanding": 500,
      "ipo_date": "2026-04-05",
      "metrics": {
        "stars": 19790,
        "forks": 2485,
        "commits_week": 181,
        "issue_response_hrs": 51.8,
        "contributors": 98
      },
      "tags": [
        "ipo-new"
      ]
    },
    "openclaude": {
      "full_name": "Gitlawb/openclaude",
      "price": 237.66,
      "prev_price": 231.95,
      "change_pct": 2.46,
      "volume_24h": 0,
      "market_cap": 118830.0,
      "shares_outstanding": 500,
      "ipo_date": "2026-04-06",
      "metrics": {
        "stars": 24421,
        "forks": 8024,
        "commits_week": 4,
        "issue_response_hrs": 168.0,
        "contributors": 90
      },
      "tags": [
        "ipo-new"
      ]
    },
    "awesomedesignmd": {
      "full_name": "VoltAgent/awesome-design-md",
      "price": 252.3,
      "prev_price": 257.18,
      "change_pct": -1.9,
      "volume_24h": 0,
      "market_cap": 126150.0,
      "shares_outstanding": 500,
      "ipo_date": "2026-04-07",
      "metrics": {
        "stars": 65567,
        "forks": 8095,
        "commits_week": 2,
        "issue_response_hrs": 31.8,
        "contributors": 4
      },
      "tags": [
        "ipo-new"
      ]
    },
    "mempalace": {
      "full_name": "milla-jovovich/mempalace",
      "price": 277.23,
      "prev_price": 304.81,
      "change_pct": -9.05,
      "volume_24h": 0,
      "market_cap": 138615.0,
      "shares_outstanding": 500,
      "ipo_date": "2026-04-09",
      "metrics": {
        "stars": 49688,
        "forks": 6513,
        "commits_week": 107,
        "issue_response_hrs": 136.8,
        "contributors": 54
      },
      "tags": [
        "ipo-new"
      ]
    },
    "careerops": {
      "full_name": "santifer/career-ops",
      "price": 236.92,
      "prev_price": 242.92,
      "change_pct": -2.47,
      "volume_24h": 0,
      "market_cap": 118460.0,
      "shares_outstanding": 500,
      "ipo_date": "2026-04-09",
      "metrics": {
        "stars": 39727,
        "forks": 8149,
        "commits_week": 13,
        "issue_response_hrs": 168.0,
        "contributors": 33
      },
      "tags": [
        "ipo-new"
      ]
    },
    "graphify": {
      "full_name": "safishamsi/graphify",
      "price": 212.69,
      "prev_price": 224.61,
      "change_pct": -5.31,
      "volume_24h": 0,
      "market_cap": 106345.0,
      "shares_outstanding": 500,
      "ipo_date": "2026-04-12",
      "metrics": {
        "stars": 34951,
        "forks": 3881,
        "commits_week": 36,
        "issue_response_hrs": 23.6,
        "contributors": 6
      },
      "tags": [
        "ipo-new"
      ]
    },
    "caveman": {
      "full_name": "JuliusBrussee/caveman",
      "price": 218.7,
      "prev_price": 222.87,
      "change_pct": -1.87,
      "volume_24h": 0,
      "market_cap": 109350.0,
      "shares_outstanding": 500,
      "ipo_date": "2026-04-14",
      "metrics": {
        "stars": 46656,
        "forks": 2454,
        "commits_week": 0,
        "issue_response_hrs": 88.5,
        "contributors": 26
      },
      "tags": [
        "ipo-new"
      ]
    }
  }
}
