{
  "trader_count": 2,
  "leaderboard": [
    {
      "username": "SolanaLeeky",
      "total_value": 11250.39,
      "pnl": 1250.39,
      "pnl_pct": 12.5,
      "trade_count": 12,
      "achievements": [
        "first-trade",
        "early-bird",
        "contrarian",
        "ipo-hunter",
        "paper-hands"
      ]
    },
    {
      "username": "neurobytex",
      "total_value": 10029.03,
      "pnl": 29.03,
      "pnl_pct": 0.3,
      "trade_count": 1,
      "achievements": [
        "first-trade",
        "contrarian"
      ]
    }
  ]
}
