{
  "trader_count": 2,
  "leaderboard": [
    {
      "username": "SolanaLeeky",
      "total_value": 11893.7,
      "pnl": 1893.7,
      "pnl_pct": 18.9,
      "trade_count": 12,
      "achievements": [
        "first-trade",
        "early-bird",
        "contrarian",
        "ipo-hunter",
        "paper-hands"
      ]
    },
    {
      "username": "neurobytex",
      "total_value": 9820.18,
      "pnl": -179.82,
      "pnl_pct": -1.8,
      "trade_count": 1,
      "achievements": [
        "first-trade",
        "contrarian"
      ]
    }
  ]
}
